{"@odata.context":"https://graph.microsoft.com/v1.0/$metadata#users","value":[{"businessPhones":[],"displayName":"Angel Javier","givenName":null,"jobTitle":null,"mail":"ajavierv@emeal.nttdata.com","mobilePhone":null,"officeLocation":null,"preferredLanguage":null,"surname":null,"userPrincipalName":"ajavierv_emeal.nttdata.com#EXT#@angeljavahotmail.onmicrosoft.com","id":"7e8fc13a-ccd0-4f91-a883-1fbab15d152a"},{"businessPhones":[],"displayName":"Angel Javier","givenName":"Angel","jobTitle":null,"mail":null,"mobilePhone":null,"officeLocation":null,"preferredLanguage":null,"surname":"Java","userPrincipalName":"angel.java@angeljavahotmail.onmicrosoft.com","id":"f1088fcb-9d24-4fe9-b8b5-f81db5f4fed6"},{"businessPhones":[],"displayName":"Angel Javier Valdez","givenName":"Angel","jobTitle":null,"mail":null,"mobilePhone":null,"officeLocation":null,"preferredLanguage":"en","surname":"Javier Valdez","userPrincipalName":"angel_java_hotmail.com#EXT#@angeljavahotmail.onmicrosoft.com","id":"f1fd45d0-dc70-47fa-a34e-a95dd2f38705"},{"businessPhones":[],"displayName":"Christian Lopez Arreguin","givenName":null,"jobTitle":null,"mail":"clopearr@emeal.nttdata.com","mobilePhone":null,"officeLocation":null,"preferredLanguage":null,"surname":null,"userPrincipalName":"clopearr_emeal.nttdata.com#EXT#@angeljavahotmail.onmicrosoft.com","id":"68f66794-1665-4f83-a122-7ead48ab1d62"},{"businessPhones":[],"displayName":"Jane Smith","givenName":"Jane","jobTitle":null,"mail":null,"mobilePhone":null,"officeLocation":null,"preferredLanguage":null,"surname":"Smith","userPrincipalName":"jane.smith@angeljavahotmail.onmicrosoft.com","id":"b04fa5fc-64df-4bb6-83e4-50c459dcf6bd"},{"businessPhones":[],"displayName":"John Doe","givenName":"John","jobTitle":null,"mail":null,"mobilePhone":null,"officeLocation":null,"preferredLanguage":null,"surname":"Doe","userPrincipalName":"john.doe@angeljavahotmail.onmicrosoft.com","id":"5004a3fe-0a89-41a2-a695-90486dafb35a"},{"businessPhones":[],"displayName":"Michael Jordan","givenName":null,"jobTitle":null,"mail":null,"mobilePhone":null,"officeLocation":null,"preferredLanguage":null,"surname":null,"userPrincipalName":"michael.jordan@angeljavahotmail.onmicrosoft.com","id":"a0516272-1111-40b5-b733-37f1d90cce5a"}]}